setup.cfg
setup.py
twistes/__init__.py
twistes/bulk_utils.py
twistes/client.py
twistes/compatability.py
twistes/consts.py
twistes/exceptions.py
twistes/parser.py
twistes/scroller.py
twistes/utilities.py
twistes/version.py
twistes.egg-info/PKG-INFO
twistes.egg-info/SOURCES.txt
twistes.egg-info/dependency_links.txt
twistes.egg-info/not-zip-safe
twistes.egg-info/requires.txt
twistes.egg-info/top_level.txt