Metadata-Version: 1.1
Name: twistes
Version: 0.1.19
Summary: Asynchronous elastic search client using Twisted and Treq
Home-page: https://github.com/avihad/twistes
Author: Avihad Menahem
Author-email: avihad87@gmail.com
License: Apache License Version 2.0
Download-URL: https://github.com/avihad/twistes/tarball/v0.1.19
Keywords: elasticsearch,async,asynchronous,twisted,treq
Platform: Any
Classifier: Development Status :: 4 - Beta
Classifier: Intended Audience :: Developers
Classifier: License :: OSI Approved :: Apache Software License
Classifier: Natural Language :: English
Classifier: Operating System :: OS Independent
Classifier: Programming Language :: Python
Classifier: Programming Language :: Python :: 2
Classifier: Programming Language :: Python :: 3
Classifier: Topic :: Software Development :: Libraries :: Python Modules
Classifier: Topic :: Software Development :: Testing
